aiogram_cli/__init__.py
aiogram_cli/__main__.py
aiogram_cli/main.py
aiogram_cli/resolver.py
aiogram_cli/wraps.py
aiogram_cli/develop/__init__.py
aiogram_cli/develop/_bot.py
aiogram_cli/develop/_dispatcher.py
aiogram_cli/develop/_polling.py
aiogram_cli/develop/_resolver.py
aiogram_cli/develop/_server_address.py
aiogram_cli/develop/_webhook.py
aiogram_cli/develop/plugin.py
aiogram_cli-1.1.0.dist-info/METADATA
aiogram_cli-1.1.0.dist-info/WHEEL
aiogram_cli-1.1.0.dist-info/entry_points.txt
aiogram_cli-1.1.0.dist-info/licenses/LICENSE.txt
aiogram_cli-1.1.0.dist-info/RECORD
