Metadata-Version: 2.3
Name: aiogram_cli
Version: 1.1.0
Project-URL: Documentation, https://github.com/aiogram/cli#readme
Project-URL: Issues, https://github.com/aiogram/cli/issues
Project-URL: Source, https://github.com/aiogram/cli
Author-email: Alex Root Junior <jroot.junior@gmail.com>
License-Expression: MIT
License-File: LICENSE.txt
Classifier: Development Status :: 4 - Beta
Classifier: Environment :: Console
Classifier: Environment :: Plugins
Classifier: License :: OSI Approved :: MIT License
Classifier: Programming Language :: Python :: 3.9
Classifier: Programming Language :: Python :: 3.10
Classifier: Programming Language :: Python :: 3.11
Classifier: Programming Language :: Python :: Implementation :: CPython
Classifier: Programming Language :: Python :: Implementation :: PyPy
Classifier: Topic :: Utilities
Requires-Python: >=3.10
Requires-Dist: aiogram<4.0.0,>=3.7.0
Requires-Dist: click-plugins~=1.1.1
Requires-Dist: click~=8.1.7
Requires-Dist: colorama~=0.4.6
Requires-Dist: watchfiles~=0.20.0
